{"sections":{"image_banner_wkUFJz":{"type":"image-banner","name":"t:sections.image-banner.presets.name","settings":{"image":"shopify:\/\/shop_images\/30_14.png","image_overlay_opacity":0,"image_height":"adapt","image_behavior":"none","desktop_content_position":"middle-center","desktop_content_alignment":"center","show_text_box":false,"color_scheme":"","stack_images_on_mobile":false,"mobile_content_alignment":"center","show_text_below":false,"linear_bg_class":""}},"main":{"type":"main-page","settings":{"padding_top":0,"padding_bottom":0}},"pagefly_section_36PYPW":{"type":"pagefly-section","name":"PageFly Section","settings":{"section_id":"pf-94452416"}},"featured_collection_LhznAP":{"type":"featured-collection","name":"t:sections.featured-collection.presets.name","settings":{"collection":"men","products_to_show":19,"title":"","heading_size":"h2","description":"","show_description":false,"description_style":"body","columns_desktop":4,"enable_desktop_slider":false,"full_width":false,"show_view_all":true,"view_all_style":"solid","color_scheme":"","image_ratio":"adapt","image_shape":"default","show_secondary_image":false,"show_vendor":false,"show_rating":false,"quick_add":"none","columns_mobile":"2","swipe_on_mobile":false,"padding_top":0,"padding_bottom":12,"linear_bg_class":""}}},"order":["image_banner_wkUFJz","pagefly_section_36PYPW","main","featured_collection_LhznAP"]}